MANIFEST.in
README.md
setup.py
stylelens_crawl_amazon/__init__.py
stylelens_crawl_amazon/aws_product_api.py
stylelens_crawl_amazon/browse_nodes.py
stylelens_crawl_amazon/item_lookup.py
stylelens_crawl_amazon/item_search.py
stylelens_crawl_amazon/search_factory.py
stylelens_crawl_amazon/stylelens_crawl.py
stylelens_crawl_amazon/util.py
stylelens_crawl_amazon.egg-info/PKG-INFO
stylelens_crawl_amazon.egg-info/SOURCES.txt
stylelens_crawl_amazon.egg-info/dependency_links.txt
stylelens_crawl_amazon.egg-info/requires.txt
stylelens_crawl_amazon.egg-info/top_level.txt
stylelens_crawl_amazon/data/__init__.py
stylelens_crawl_amazon/data/attribute_fabric.txt
stylelens_crawl_amazon/data/attribute_part.txt
stylelens_crawl_amazon/data/attribute_shape.txt
stylelens_crawl_amazon/data/attribute_style.txt
stylelens_crawl_amazon/data/attribute_texture.txt
stylelens_crawl_amazon/data/browse_node_cache.txt
stylelens_crawl_amazon/data/browse_nodes_black.txt
stylelens_crawl_amazon/data/browse_nodes_white.txt
stylelens_crawl_amazon/data/categories.txt
stylelens_crawl_amazon/data/item_lookup_response_groups.txt
stylelens_crawl_amazon/data/item_search_response_groups.txt
stylelens_crawl_amazon/data/search_indices.txt
stylelens_crawl_amazon/data/sorts_Apparel.txt
stylelens_crawl_amazon/data/sorts_Fashion.txt
stylelens_crawl_amazon/model/__init__.py
stylelens_crawl_amazon/model/base_model_.py
stylelens_crawl_amazon/model/item.py
stylelens_crawl_amazon/model/item_image.py
stylelens_crawl_amazon/model/item_price.py
stylelens_crawl_amazon/model/item_search_data.py