Metadata-Version: 1.0
Name: stylelens-crawl-amazon
Version: 0.0.64
Summary: stylelens-crawl-amazon
Home-page: UNKNOWN
Author: UNKNOWN
Author-email: master@bluehack.net
License: UNKNOWN
Keywords: BlueLens,stylelens-crawl-amazon
Platform: UNKNOWN
